{
"type": "FeatureCollection",
"name": "puntos_muestreo",
"crs": { "type": "name", "properties": { "name": "urn:ogc:def:crs:OGC:1.3:CRS84" } },
"features": [
{ "type": "Feature", "properties": { "OBJECTID": 1, "LONG": -75.5009816667, "ALTITUD": 1.1634380555599999, "PTO": "IE LA RASTRA", "F4": null, "F5": null, "F6": null, "F7": null, "F8": null, "F9": null, "F10": "d" }, "geometry": { "type": "Point", "coordinates": [ -75.50098166674519, 1.163438056335034 ] } },
{ "type": "Feature", "properties": { "OBJECTID": 2, "LONG": -75.256443055600002, "ALTITUD": 0.70079694444399998, "PTO": "SOLANO", "F4": null, "F5": null, "F6": null, "F7": null, "F8": null, "F9": null, "F10": null }, "geometry": { "type": "Point", "coordinates": [ -75.256443055966841, 0.700796943742508 ] } },
{ "type": "Feature", "properties": { "OBJECTID": 3, "LONG": -75.174393055600007, "ALTITUD": 0.47404611111099998, "PTO": "MECAYA", "F4": null, "F5": null, "F6": null, "F7": null, "F8": null, "F9": null, "F10": null }, "geometry": { "type": "Point", "coordinates": [ -75.174393055728856, 0.474046110896774 ] } },
{ "type": "Feature", "properties": { "OBJECTID": 4, "LONG": -75.109803888900004, "ALTITUD": 0.47645777777800002, "PTO": "LAGO PUERTO PRINCIPE", "F4": null, "F5": null, "F6": null, "F7": null, "F8": null, "F9": null, "F10": null }, "geometry": { "type": "Point", "coordinates": [ -75.109803888600396, 0.476457777645862 ] } },
{ "type": "Feature", "properties": { "OBJECTID": 5, "LONG": -75.035328055600004, "ALTITUD": 0.48651916666700001, "PTO": "PEÑAS BLANCAS", "F4": null, "F5": null, "F6": null, "F7": null, "F8": null, "F9": null, "F10": null }, "geometry": { "type": "Point", "coordinates": [ -75.035328056117592, 0.486519167169803 ] } },
{ "type": "Feature", "properties": { "OBJECTID": 6, "LONG": -75.039812777799995, "ALTITUD": 0.48830138888899999, "PTO": "CAÑO PEÑAS BLANCAS", "F4": null, "F5": null, "F6": null, "F7": null, "F8": null, "F9": null, "F10": null }, "geometry": { "type": "Point", "coordinates": [ -75.039812778208116, 0.488301388601071 ] } },
{ "type": "Feature", "properties": { "OBJECTID": 7, "LONG": -75.0104611111, "ALTITUD": 0.437855, "PTO": "PETERRUMBE", "F4": null, "F5": null, "F6": null, "F7": null, "F8": null, "F9": null, "F10": null }, "geometry": { "type": "Point", "coordinates": [ -75.0104611108261, 0.437854999575692 ] } },
{ "type": "Feature", "properties": { "OBJECTID": 8, "LONG": -75.503081944399995, "ALTITUD": 1.16635388889, "PTO": "LA RASTRA", "F4": null, "F5": null, "F6": null, "F7": null, "F8": null, "F9": null, "F10": null }, "geometry": { "type": "Point", "coordinates": [ -75.503081943785446, 1.166353888878655 ] } },
{ "type": "Feature", "properties": { "OBJECTID": 9, "LONG": -75.916751111099998, "ALTITUD": 0.98152694444400002, "PTO": "CALLE SAN JUAN", "F4": null, "F5": null, "F6": null, "F7": null, "F8": null, "F9": null, "F10": null }, "geometry": { "type": "Point", "coordinates": [ -75.916751110741075, 0.981526944031707 ] } },
{ "type": "Feature", "properties": { "OBJECTID": 10, "LONG": -76.018773611100002, "ALTITUD": 1.0529566666700001, "PTO": "IE LA PRADERA", "F4": null, "F5": null, "F6": null, "F7": null, "F8": null, "F9": null, "F10": null }, "geometry": { "type": "Point", "coordinates": [ -76.018773611390316, 1.052956666783552 ] } },
{ "type": "Feature", "properties": { "OBJECTID": 11, "LONG": -76.000046111100005, "ALTITUD": 1.03765888889, "PTO": "FIDELICIA", "F4": null, "F5": null, "F6": null, "F7": null, "F8": null, "F9": null, "F10": null }, "geometry": { "type": "Point", "coordinates": [ -76.000046111377884, 1.037658888739408 ] } },
{ "type": "Feature", "properties": { "OBJECTID": 12, "LONG": -75.929978888899996, "ALTITUD": 0.99750694444400001, "PTO": "EL CONQUISTADOR", "F4": null, "F5": null, "F6": null, "F7": null, "F8": null, "F9": null, "F10": null }, "geometry": { "type": "Point", "coordinates": [ -75.929978889095239, 0.997506943879519 ] } },
{ "type": "Feature", "properties": { "OBJECTID": 13, "LONG": -75.929891944399998, "ALTITUD": 0.99535888888900004, "PTO": "IE EL CONQUISTADOR", "F4": null, "F5": null, "F6": null, "F7": null, "F8": null, "F9": null, "F10": null }, "geometry": { "type": "Point", "coordinates": [ -75.929891944025201, 0.995358888917353 ] } },
{ "type": "Feature", "properties": { "OBJECTID": 14, "LONG": -75.919102777800006, "ALTITUD": 1.0342533333299999, "PTO": "CURRILLO", "F4": null, "F5": null, "F6": null, "F7": null, "F8": null, "F9": null, "F10": null }, "geometry": { "type": "Point", "coordinates": [ -75.919102777985472, 1.034253332788619 ] } },
{ "type": "Feature", "properties": { "OBJECTID": 15, "LONG": -75.064194444400002, "ALTITUD": 0.47619583333299997, "PTO": "PUERTO PRINCIPE", "F4": null, "F5": null, "F6": null, "F7": null, "F8": null, "F9": null, "F10": null }, "geometry": { "type": "Point", "coordinates": [ -75.06419444376975, 0.476195833204954 ] } }
]
}
